[
  {
    "chain_id": 10,
    "hash": "0xbf470ac5aa018c4bc15fbdc62fd43d428662c9d6983f68a975f593171902cd2b",
    "timestamp": "2024-01-05T20:38:45+00:00",
    "interpretation": {
      "id": "clrakug1e000tps8hgq8eauql",
      "actions": [
        {
          "id": "clrakug1e000tps8hgq8eauql",
          "action": "NATIVE_RECEIVE",
          "address": "0xFbd80Fe5cE1ECe895845Fd131bd621e2B6A1345F"
        }
      ],
      "asset_changes": [
        {
          "id": "clrakugxw000vps8hbj32jy2v",
          "address": "0x4fd9D0eE6D6564E80A9Ee00c0163fC952d0A45Ed",
          "amount": 1000000000000000,
          "before_amount": 2412758692803309,
          "after_amount": 1412758692803309,
          "token": {
            "id": "clota6rxh0000l308gsist1ix",
            "address": "0x0000000000000000000000000000000000000000",
            "chain_id": 10,
            "name": "Ether",
            "symbol": "ETH",
            "decimals": 18,
            "amount": 0,
            "balance_usd": 0,
            "group": null
          }
        },
        {
          "id": "clrakuhea000wps8h48bavoly",
          "address": "0xFbd80Fe5cE1ECe895845Fd131bd621e2B6A1345F",
          "amount": 1000000000000000,
          "before_amount": 1000000000000000,
          "after_amount": 2000000000000000,
          "token": {
            "id": "clota6rxh0000l308gsist1ix",
            "address": "0x0000000000000000000000000000000000000000",
            "chain_id": 10,
            "name": "Ether",
            "symbol": "ETH",
            "decimals": 18,
            "amount": 0,
            "balance_usd": 0,
            "group": null
          }
        }
      ]
    }
  },
  {
    "chain_id": 137,
    "hash": "0x2c64e1da0c8186c1d64edc382cbb48e8ca60917c9dca240ffd5659cd5595e282",
    "timestamp": "2023-12-30T03:35:01+00:00",
    "interpretation": {
      "id": "clrakw0wy002vps8hohxvtn1s",
      "actions": [
        {
          "id": "clrakw0wy002vps8hohxvtn1s",
          "action": "ERC20_RECEIVE",
          "address": "0xFbd80Fe5cE1ECe895845Fd131bd621e2B6A1345F"
        }
      ],
      "asset_changes": [
        {
          "id": "clrakw1fq002xps8h5rox9fh1",
          "address": "0xFbd80Fe5cE1ECe895845Fd131bd621e2B6A1345F",
          "amount": 100000,
          "before_amount": 155815,
          "after_amount": 55815,
          "token": {
            "id": "cloupmjv60002jy08hud4y7mb",
            "address": "0xc2132D05D31c914a87C6611C10748AEb04B58e8F",
            "chain_id": 137,
            "name": null,
            "symbol": "USDT",
            "decimals": 6,
            "amount": 0,
            "balance_usd": 0,
            "group": null
          }
        },
        {
          "id": "clrakw1wa002zps8hefk3aloz",
          "address": "0x4fd9D0eE6D6564E80A9Ee00c0163fC952d0A45Ed",
          "amount": 100000,
          "before_amount": 100000,
          "after_amount": 200000,
          "token": {
            "id": "cloupmjv60002jy08hud4y7mb",
            "address": "0xc2132D05D31c914a87C6611C10748AEb04B58e8F",
            "chain_id": 137,
            "name": null,
            "symbol": "USDT",
            "decimals": 6,
            "amount": 0,
            "balance_usd": 0,
            "group": null
          }
        }
      ]
    }
  },
  {
    "chain_id": 137,
    "hash": "0xc8e327667f062843195f77db4374afdb29f8ed2fce0e88c315f2c4110f59ed44",
    "timestamp": "2023-12-24T23:26:16+00:00",
    "interpretation": null
  },
  {
    "chain_id": 137,
    "hash": "0xbae537eb880ad0345c62f1b357cdc330840d0f4516fc2709a6929b3f78c10e11",
    "timestamp": "2023-12-22T03:30:17+00:00",
    "interpretation": null
  },
  {
    "chain_id": 137,
    "hash": "0x73f94e289d4a798349ad10d57f5130221050ffb56ea27baa560a78acac3c51f4",
    "timestamp": "2023-12-20T20:57:39+00:00",
    "interpretation": null
  },
  {
    "chain_id": 137,
    "hash": "0xf49f28d44a30b852ff44197b52a9304f8b4d0f99c1ff17ca88b7971637a801b2",
    "timestamp": "2023-12-10T02:00:39+00:00",
    "interpretation": null
  }
]
