[
  {
    "id": "clr9y4rm40003re8h7irefr13",
    "entity": "USER_OPERATION",
    "operation": "CREATE",
    "timestamp": "2024-01-12T01:14:54.029+00:00",
    "address": "0xFbd80Fe5cE1ECe895845Fd131bd621e2B6A1345F"
  },
  {
    "id": "clr9y44is0001re8hbssu82mb",
    "entity": "SIGNATURE",
    "operation": "CREATE",
    "timestamp": "2024-01-12T01:14:24.100+00:00",
    "address": "0xFbd80Fe5cE1ECe895845Fd131bd621e2B6A1345F"
  },
  {
    "id": "clr12co490003ol8ipshssdxo",
    "entity": "WALLET",
    "operation": "UPDATE",
    "timestamp": "2024-01-05T20:03:05.625+00:00",
    "address": "0xFbd80Fe5cE1ECe895845Fd131bd621e2B6A1345F"
  },
  {
    "id": "clr12c7i20001ol8igrvombxd",
    "entity": "WALLET",
    "operation": "UPDATE",
    "timestamp": "2024-01-05T20:02:44.091+00:00",
    "address": "0xFbd80Fe5cE1ECe895845Fd131bd621e2B6A1345F"
  },
  {
    "id": "clqzwb8zu001hqy8izuapvleu",
    "entity": "WALLET",
    "operation": "UPDATE",
    "timestamp": "2024-01-05T00:26:15.498+00:00",
    "address": "0xFbd80Fe5cE1ECe895845Fd131bd621e2B6A1345F"
  },
  {
    "id": "clqzwb350001fqy8imipzps51",
    "entity": "WALLET",
    "operation": "UPDATE",
    "timestamp": "2024-01-05T00:26:07.908+00:00",
    "address": "0xFbd80Fe5cE1ECe895845Fd131bd621e2B6A1345F"
  },
  {
    "id": "clqozjcg00015qy8i7tjebh8n",
    "entity": "WALLET",
    "operation": "UPDATE",
    "timestamp": "2023-12-28T09:11:04.129+00:00",
    "address": "0xFbd80Fe5cE1ECe895845Fd131bd621e2B6A1345F"
  },
  {
    "id": "clqozj59b0013qy8ixwrbcw2c",
    "entity": "WALLET",
    "operation": "UPDATE",
    "timestamp": "2023-12-28T09:10:54.815+00:00",
    "address": "0xFbd80Fe5cE1ECe895845Fd131bd621e2B6A1345F"
  },
  {
    "id": "clqofitsl000zqy8ipgsnsv2q",
    "entity": "WALLET",
    "operation": "UPDATE",
    "timestamp": "2023-12-27T23:50:47.637+00:00",
    "address": "0xFbd80Fe5cE1ECe895845Fd131bd621e2B6A1345F"
  },
  {
    "id": "clqofipfc000xqy8itvwhsaw3",
    "entity": "WALLET",
    "operation": "UPDATE",
    "timestamp": "2023-12-27T23:50:41.977+00:00",
    "address": "0xFbd80Fe5cE1ECe895845Fd131bd621e2B6A1345F"
  }
]
